cat_dj/__init__.py
cat_dj/cat_dj.py
cat_dj/cli.py
cat_dj/dj_music_mixer.py
cat_dj/video_loop_processor.py
cat_dj-0.1.2.dist-info/METADATA
cat_dj-0.1.2.dist-info/WHEEL
cat_dj-0.1.2.dist-info/entry_points.txt
cat_dj-0.1.2.dist-info/RECORD
