Metadata-Version: 2.1
Name: cat-dj
Version: 0.1.2
Summary: DJミックスとビデオループを作成するPythonパッケージ
Author: Maki
Author-email: sunwood.ai.labs@gmail.com
Requires-Python: >=3.10,<4.0
Classifier: Programming Language :: Python :: 3
Classifier: Programming Language :: Python :: 3.10
Classifier: Programming Language :: Python :: 3.11
Classifier: Programming Language :: Python :: 3.12
Requires-Dist: loguru (>=0.7.2,<0.8.0)
Requires-Dist: pydub (>=0.25.1,<0.26.0)
